pyspawn/__init__.py
pyspawn/checkpoint.py
pyspawn/_graph/__init__.py
pyspawn/_graph/graph_builder.py
pyspawn/_graph/relationship.py
pyspawn/_graph/table.py
pyspawn/_graph/temporal_table.py
pyspawn/adapters/__init__.py
pyspawn/adapters/_db_adapter.py
pyspawn/adapters/_pg_adapter.py
pyspawn/adapters/_sql_server_adapter.py
pyspawn-1.2.3.dist-info/LICENCE
pyspawn-1.2.3.dist-info/METADATA
pyspawn-1.2.3.dist-info/WHEEL
pyspawn-1.2.3.dist-info/top_level.txt
pyspawn-1.2.3.dist-info/RECORD
