Metadata-Version: 2.1
Name: pyspawn
Version: 1.2.3
Summary: Intelligent database cleaner for integration tests ported from Jbogard/Respawn.
Home-page: https://github.com/Tsanton/pyspawn
Author: Tobias Antonsen
Author-email: tobias@tsant.no
License: UNKNOWN
Platform: UNKNOWN
Classifier: Development Status :: 5 - Production/Stable
Classifier: Programming Language :: Python :: 3.6
Classifier: Programming Language :: Python :: 3.7
Classifier: Programming Language :: Python :: 3.8
Classifier: Programming Language :: Python :: 3.9
Classifier: Programming Language :: Python :: 3.10
Classifier: Intended Audience :: Developers
Classifier: License :: OSI Approved :: Apache Software License
Classifier: Operating System :: OS Independent
Requires-Python: >=3.6
Requires-Dist: dataclasses
